imaction/__init__.py
imaction/as_action.py
imaction/tests.py
imaction-0.0.1.dist-info/DESCRIPTION.rst
imaction-0.0.1.dist-info/METADATA
imaction-0.0.1.dist-info/RECORD
imaction-0.0.1.dist-info/WHEEL
imaction-0.0.1.dist-info/metadata.json
imaction-0.0.1.dist-info/top_level.txt
